sendgrowl/__init__.py
sendgrowl/__main__.py
sendgrowl/__meta__.py
sendgrowl/__version__.py
sendgrowl/growl.ini
sendgrowl/growl.png
sendgrowl/growl.py
sendgrowl-0.73.dist-info/METADATA
sendgrowl-0.73.dist-info/WHEEL
sendgrowl-0.73.dist-info/entry_points.txt
sendgrowl-0.73.dist-info/top_level.txt
sendgrowl-0.73.dist-info/RECORD
