Metadata-Version: 2.1
Name: sendgrowl
Version: 0.73
Summary: simple send notify to growl with multiple host and port
Home-page: https://github.com/cumulus13/sendgrowl
Download-URL: https://github.com/cumulus13/sendgrowl/tarball/master
Author: Hadi Cahyadi LD
Author-email: cumulus13@gmail.com
Maintainer: cumulus13 Team
Maintainer-email: cumulus13@gmail.com
License: MIT
Project-URL: Documentation, https://github.com/cumulus13/sendgrowl
Project-URL: Code, https://github.com/cumulus13/sendgrowl
Keywords: growl windows linux gntp gntplib 23053
Classifier: Development Status :: 5 - Production/Stable
Classifier: Environment :: Console
Classifier: Intended Audience :: Developers
Classifier: License :: OSI Approved :: MIT License
Classifier: Operating System :: OS Independent
Classifier: Programming Language :: Python :: 3
Classifier: Topic :: Software Development :: Libraries :: Python Modules
Requires-Python: >=3.0
Requires-Dist: gntplib
Requires-Dist: argparse
Requires-Dist: configset
Requires-Dist: pydebugger
